example_pkg/__init__.py
panacia-0.0.1.dist-info/LICENSE
panacia-0.0.1.dist-info/METADATA
panacia-0.0.1.dist-info/WHEEL
panacia-0.0.1.dist-info/top_level.txt
panacia-0.0.1.dist-info/RECORD
