Metadata-Version: 2.1
Name: panacia
Version: 0.0.1
Summary: A compendium of Medical Data Science tools developed by OpenVessel
Home-page: https://github.com/pypa/sampleproject
Author: OpenVessel
Author-email: Openvessel@openvessel.org
License: UNKNOWN
Project-URL: Bug Tracker, https://github.com/pypa/sampleproject/issues
Platform: UNKNOWN
Classifier: Programming Language :: Python :: 3
Classifier: License :: OSI Approved :: MIT License
Classifier: Operating System :: OS Independent
Requires-Python: >=3.6
